Workbook
Name Aporte: Dashboard!$D$13
Name patrimonio: Dashboard!$D$16
Name qtd_anos: Dashboard!$D$14
Name Rendimento_carteira: Dashboard!$D$9
Name salario: Dashboard!$D$8
Name sugetao_investimento: Dashboard!$D$10
Name taxa_mensal: Dashboard!$D$15

Sheet Perguntas de negocio
A1: Perguntas:
A2: 1) Quanto investir por mês?
A3: 2) Por quantos anos?
A4: 3) Taxa de rendimento mensal?
A5: 4) Patrimônio acumulado?
A6: 5) Dividendos mensais
A15: CHAVE | B15: Perfil | C15: Tipo de FII | D15: %
A16: Conservador-Papel | B16: Conservador | C16: Papel | D16: 0.3
A17: Conservador-Tijolo | B17: Conservador | C17: Tijolo | D17: 0.5
A18: Conservador-Híbridos | B18: Conservador | C18: Híbridos | D18: 0.1
A19: Conservador-FOFs | B19: Conservador | C19: FOFs | D19: 0.1
A20: Conservador-Desenvolvimento | B20: Conservador | C20: Desenvolvimento | D20: 0
A21: Conservador-Hotelarias | B21: Conservador | C21: Hotelarias | D21: 0
A22: =B22&"-"&C22 -> Moderado-Papel | B22: Moderado | C22: Papel | D22: 0.32
A23: =B23&"-"&C23 -> Moderado-Tijolo | B23: Moderado | C23: Tijolo | D23: 0.4
A24: =B24&"-"&C24 -> Moderado-Híbridos | B24: Moderado | C24: Híbridos | D24: 0.08
A25: =B25&"-"&C25 -> Moderado-FOFs | B25: Moderado | C25: FOFs | D25: 0.1
A26: =B26&"-"&C26 -> Moderado-Desenvolvimento | B26: Moderado | C26: Desenvolvimento | D26: 0.1
A27: =B27&"-"&C27 -> Moderado-Hotelarias | B27: Moderado | C27: Hotelarias | D27: 0.1
A28: =B28&"-"&C28 -> Agressivo-Papel | B28: Agressivo | C28: Papel | D28: 0.5
A29: =B29&"-"&C29 -> Agressivo-Tijolo | B29: Agressivo | C29: Tijolo | D29: 0.1
A30: =B30&"-"&C30 -> Agressivo-Híbridos | B30: Agressivo | C30: Híbridos | D30: 0.05
A31: =B31&"-"&C31 -> Agressivo-FOFs | B31: Agressivo | C31: FOFs | D31: 0.05
A32: =B32&"-"&C32 -> Agressivo-Desenvolvimento | B32: Agressivo | C32: Desenvolvimento | D32: 0.2
A33: =B33&"-"&C33 -> Agressivo-Hotelarias | B33: Agressivo | C33: Hotelarias | D33: 0.1

Sheet Dashboard
B7: CONFIGURAÇÕES
B8: Salário | D8: 5000
B9: Rendimento da carteira | D9: 0.01
B10: Sugestão de investimento | D10: =D8*30% -> 1500
B12: INVESTIMENTO MENSAL
B13: 1) Quanto investir por mês? | D13: 500
B14: 2) Por quantos anos? | D14: 5
B15: 3) Taxa de rendimento mensal? | D15: 0.0108
B16: 4) Patrimônio acumulado? | D16: =FV(taxa_mensal,qtd_anos*12,-Aporte) -> 41902.01
B17: 5) Dividendos mensais | D17: =patrimonio*1% -> 419.0201
B19: Cenários | D19: Dividendo
A20: 2 | B20: Quanto em 2 anos? | C20: =FV($D$15,A20*12,-$D$13) -> 13615.432 | D20: =C20*Rendimento_carteira -> 136.15432
A21: 5 | B21: Quanto em 5 anos? | C21: =FV($D$15,A21*12,-$D$13) -> 41902.01 | D21: =C21*Rendimento_carteira -> 419.0201
A22: 10 | B22: Quanto em 10 anos? | C22: =FV($D$15,A22*12,-$D$13) -> 121728.83 | D22: =C22*Rendimento_carteira -> 1217.2883
A23: 20 | B23: Quanto em 20 anos? | C23: =FV($D$15,A23*12,-$D$13) -> 563524.5 | D23: =C23*Rendimento_carteira -> 5635.245
A24: 30 | B24: Quanto em 30 anos? | C24: =FV($D$15,A24*12,-$D$13) -> 2166952.4 | D24: =C24*Rendimento_carteira -> 21669.524
B26: Perfil | C26: Agressivo
B27: Valor a ser investido por mês | C27: =Aporte -> 500
B29: TIPO DE FII | C29: Percentual Sugerido | D29: Valores
B30: Papel | C30: =_xlfn.XLOOKUP($C$26&"-"&B30,'Perguntas de negocio'!$A$16:$A$33,'Perguntas de negocio'!$D$16:$D$33) -> 0.5 | D30: =C30*$C$27 -> 250
B31: Tijolo | C31: =_xlfn.XLOOKUP($C$26&"-"&B31,'Perguntas de negocio'!$A$16:$A$33,'Perguntas de negocio'!$D$16:$D$33) -> 0.1 | D31: =C31*$C$27 -> 50
B32: Híbridos | C32: =_xlfn.XLOOKUP($C$26&"-"&B32,'Perguntas de negocio'!$A$16:$A$33,'Perguntas de negocio'!$D$16:$D$33) -> 0.05 | D32: =C32*$C$27 -> 25
B33: FOFs | C33: =_xlfn.XLOOKUP($C$26&"-"&B33,'Perguntas de negocio'!$A$16:$A$33,'Perguntas de negocio'!$D$16:$D$33) -> 0.05 | D33: =C33*$C$27 -> 25
B34: Desenvolvimento | C34: =_xlfn.XLOOKUP($C$26&"-"&B34,'Perguntas de negocio'!$A$16:$A$33,'Perguntas de negocio'!$D$16:$D$33) -> 0.2 | D34: =C34*$C$27 -> 100
B35: Hotelarias | C35: =_xlfn.XLOOKUP($C$26&"-"&B35,'Perguntas de negocio'!$A$16:$A$33,'Perguntas de negocio'!$D$16:$D$33) -> 0.1 | D35: =C35*$C$27 -> 50
